pydantic_extra/__init__.py
pydantic_extra/db.py
pydantic_extra/smtp.py
pydantic_extra-1.0.0.dist-info/LICENSE
pydantic_extra-1.0.0.dist-info/METADATA
pydantic_extra-1.0.0.dist-info/WHEEL
pydantic_extra-1.0.0.dist-info/top_level.txt
pydantic_extra-1.0.0.dist-info/RECORD
