Metadata-Version: 2.1
Name: pydantic-extra
Version: 1.0.0
Summary: Готовые модели pydantic для частых задач
Author-email: Ярыкин Евгений <pypi@zedzhen.ru>
License: The zlib/libpng License
Project-URL: source, https://github.com/zedzhen/pydantic-extra
Requires-Python: >=3.8
License-File: LICENSE
Requires-Dist: pydantic~=2.10
Requires-Dist: typing-extensions!=4.12.0,<4.13,>=4.10
Provides-Extra: db
Requires-Dist: sqlalchemy~=2.0; extra == "db"
